mpythonlinklib/__init__.py
mpythonlinklib-0.0.2.dist-info/LICENSE
mpythonlinklib-0.0.2.dist-info/METADATA
mpythonlinklib-0.0.2.dist-info/WHEEL
mpythonlinklib-0.0.2.dist-info/top_level.txt
mpythonlinklib-0.0.2.dist-info/RECORD
