Metadata-Version: 2.1
Name: mpythonlinklib
Version: 0.0.2
Summary: Used for UDP control of labplus products
Home-page: 
Author: TMiracleOW
Author-email: 1037085395@163.com
License: MIT
Classifier: Development Status :: 3 - Alpha
Classifier: Intended Audience :: Developers
Classifier: License :: OSI Approved :: MIT License
Classifier: Programming Language :: Python :: 3
Classifier: Programming Language :: Python :: 3.7
Classifier: Programming Language :: Python :: 3.8
Classifier: Programming Language :: Python :: 3.9
License-File: LICENSE
